cycparser/__init__.py
cycparser/data.py
cycparser/defaults.py
cycparser/parsing/__init__.py
cycparser/parsing/compounds.py
cycparser/parsing/enzymes.py
cycparser/parsing/monomer_annotation.py
cycparser/parsing/monomer_sequences.py
cycparser/parsing/protein_complexes.py
cycparser/parsing/reactions.py
cycparser/parsing/shared.py
cycparser/py.typed
cycparser/repairing/__init__.py
cycparser/repairing/fix_add_important_cpds.py
cycparser/repairing/fix_create_compartment_variants.py
cycparser/repairing/fix_create_reaction_variants.py
cycparser/repairing/fix_filter_garbage.py
cycparser/repairing/fix_get_gpr_association.py
cycparser/repairing/fix_get_highest_compound_type.py
cycparser/repairing/fix_get_kinetic_data.py
cycparser/repairing/fix_set_reaction_stoichiometry.py
cycparser/repairing/fix_unify_reaction_direction.py
cycparser/utils.py
cycparser-1.2.112.dist-info/LICENSE
cycparser-1.2.112.dist-info/WHEEL
cycparser-1.2.112.dist-info/METADATA
cycparser-1.2.112.dist-info/RECORD
