Metadata-Version: 2.1
Name: cycparser
Version: 1.2.112
Summary: 
Author: Marvin van Aalst
Author-email: marvin.vanaalst@gmail.com
Requires-Python: >=3.8,<4.0
Classifier: Programming Language :: Python :: 3
Classifier: Programming Language :: Python :: 3.8
Classifier: Programming Language :: Python :: 3.9
Classifier: Programming Language :: Python :: 3.10
Classifier: Programming Language :: Python :: 3.11
Requires-Dist: gitchangelog (>=3.0.4,<4.0.0)
